Random_Enemy_Attributes/Random_Enemy_Attributes.cpython-311-x86_64-linux-gnu.so
Random_Enemy_Attributes-1.0.4.3.dist-info/LICENSE
Random_Enemy_Attributes-1.0.4.3.dist-info/METADATA
Random_Enemy_Attributes-1.0.4.3.dist-info/RECORD
Random_Enemy_Attributes-1.0.4.3.dist-info/top_level.txt
Random_Enemy_Attributes-1.0.4.3.dist-info/WHEEL
