Metadata-Version: 2.1
Name: Random_Enemy_Attributes
Version: 1.0.4.3
Summary: Randomizes enemy stat values for most of the enemies in the game Metroid Prime.
Home-page: https://github.com/Fantaselion/PARAMETEREDITOR
Author: Fantaselion
Author-email: fantaselion@gmail.com
License: MIT
License-File: LICENSE
